Metadata-Version: 2.1
Name: odoo13-addon-base-tier-validation
Version: 13.0.1.9.2
Summary: Implement a validation process based on tiers.
Home-page: https://github.com/OCA/server-ux
Author: ForgeFlow, Odoo Community Association (OCA)
Author-email: support@odoo-community.org
License: AGPL-3
Platform: UNKNOWN
Classifier: Programming Language :: Python
Classifier: Framework :: Odoo
Classifier: Framework :: Odoo :: 13.0
Classifier: License :: OSI Approved :: GNU Affero General Public License v3
Classifier: Development Status :: 6 - Mature
Requires-Python: >=3.5
Requires-Dist: odoo <13.1dev,>=13.0a
